ltiarithmetic.py
ltiarithmetic/__init__.py
ltiarithmetic/lti.py
lti_arithmetic-1.0.0.post1.dist-info/LICENSE
lti_arithmetic-1.0.0.post1.dist-info/METADATA
lti_arithmetic-1.0.0.post1.dist-info/WHEEL
lti_arithmetic-1.0.0.post1.dist-info/top_level.txt
lti_arithmetic-1.0.0.post1.dist-info/RECORD
