Metadata-Version: 2.1
Name: lti-arithmetic
Version: 1.0.0.post1
Summary: Arithmetical manipulation for scipy.signal.lti TransferFunction
Home-page: https://github.com/jmwilson/lti-arithmetic
Author: James Wilson
Author-email: jmw@jmw.name
License: UNKNOWN
Platform: UNKNOWN
Classifier: License :: OSI Approved :: MIT License
Classifier: Topic :: Scientific/Engineering
License-File: LICENSE
Requires-Dist: numpy (>=1.4)
Requires-Dist: scipy
